CHANGES.rst
CONTRIBUTORS.rst
MANIFEST.in
README.rst
setup.cfg
setup.py
docs/LICENSE.GPL
docs/LICENSE.txt
src/collective/__init__.py
src/collective.weather.egg-info/PKG-INFO
src/collective.weather.egg-info/SOURCES.txt
src/collective.weather.egg-info/dependency_links.txt
src/collective.weather.egg-info/namespace_packages.txt
src/collective.weather.egg-info/not-zip-safe
src/collective.weather.egg-info/requires.txt
src/collective.weather.egg-info/top_level.txt
src/collective/weather/__init__.py
src/collective/weather/config.py
src/collective/weather/configure.zcml
src/collective/weather/controlpanel.py
src/collective/weather/interfaces.py
src/collective/weather/testing.py
src/collective/weather/top_bar_weather.pt
src/collective/weather/viewlet.py
src/collective/weather/vocabularies.py
src/collective/weather/weather_utility.py
src/collective/weather/Extensions/Install.py
src/collective/weather/Extensions/__init__.py
src/collective/weather/browser/__init__.py
src/collective/weather/browser/configure.zcml
src/collective/weather/browser/current_weather.py
src/collective/weather/browser/css/style.css
src/collective/weather/browser/icons/NA.png
src/collective/weather/browser/icons/clear-day-icon.png
src/collective/weather/browser/icons/clear-night-icon.png
src/collective/weather/browser/icons/cloudy-icon.png
src/collective/weather/browser/icons/fog-icon.png
src/collective/weather/browser/icons/hail-icon.png
src/collective/weather/browser/icons/partly-cloudy-day-icon.png
src/collective/weather/browser/icons/partly-cloudy-night-icon.png
src/collective/weather/browser/icons/rain-icon.png
src/collective/weather/browser/icons/sleet-icon.png
src/collective/weather/browser/icons/snow-icon.png
src/collective/weather/browser/icons/thunderstorm-icon.png
src/collective/weather/browser/icons/tornado-icon.png
src/collective/weather/browser/icons/weather.png
src/collective/weather/browser/icons/wind-icon.png
src/collective/weather/browser/js/weather.js
src/collective/weather/browser/templates/current_weather.pt
src/collective/weather/locales/collective.weather.pot
src/collective/weather/locales/manual.pot
src/collective/weather/locales/plone.pot
src/collective/weather/locales/es/LC_MESSAGES/collective.weather.mo
src/collective/weather/locales/es/LC_MESSAGES/collective.weather.po
