Metadata-Version: 1.1
Name: collective.weather
Version: 1.0a4
Summary: A Plone package to display the current weather at selected locations inside a portlet or viewlet.
Home-page: https://github.com/collective/collective.weather
Author: OpenMultimedia
Author-email: contacto@openmultimedia.biz
License: GPLv2
Keywords: api google noaa plone weather yahoo
Platform: UNKNOWN
Classifier: Development Status :: 3 - Alpha
Classifier: Environment :: Web Environment
Classifier: Framework :: Plone
Classifier: Framework :: Plone :: 4.1
Classifier: Framework :: Plone :: 4.2
Classifier: Framework :: Plone :: 4.3
Classifier: Intended Audience :: System Administrators
Classifier: License :: OSI Approved :: GNU General Public License v2 (GPLv2)
Classifier: Operating System :: OS Independent
Classifier: Programming Language :: JavaScript
Classifier: Programming Language :: Python
Classifier: Programming Language :: Python :: 2.6
Classifier: Programming Language :: Python :: 2.7
Classifier: Topic :: Software Development :: Libraries :: Python Modules
